personal_interfaces/__init__.py
personal_interfaces/_version.py
personal_interfaces/base_api.py
personal_interfaces/database_handler.py
personal_interfaces/jwt_handler.py
personal_interfaces/logger.py
personal_interfaces/server_handler.py
personal_interfaces/graphql/__init__.py
personal_interfaces/graphql/_utils.py
personal_interfaces/graphql/interface.py
personal_interfaces/graphql/models_builder.py
personal_interfaces/graphql/mutation_builder.py
personal_interfaces/graphql/query_builder.py
personal_interfaces/graphql/connectors/__init__.py
personal_interfaces/graphql/connectors/deta_db.py
personal_interfaces/graphql/connectors/template.py
personal_interfaces/graphql/connectors/tinydb_db.py
personal_interfaces-0.4.2.dist-info/LICENSE
personal_interfaces-0.4.2.dist-info/METADATA
personal_interfaces-0.4.2.dist-info/WHEEL
personal_interfaces-0.4.2.dist-info/top_level.txt
personal_interfaces-0.4.2.dist-info/RECORD
