Metadata-Version: 2.1
Name: personal-interfaces
Version: 0.4.2
Home-page: https://github.com/ricardoleal20/personal_interface/
Author: Ricardo Leal
Author-email: ricardo.lealpz@gmail.com
Maintainer: Ricardo Leal
Maintainer-email: ricardo.lealpz@gmail.com
Project-URL: Bug Reports, https://github.com/ricardoleal20/personal_interface/issues
Keywords: development,personal_usage
Classifier: Topic :: Software Development :: Build Tools
Classifier: Programming Language :: Python :: 3.8
Classifier: Programming Language :: Python :: 3.9
Classifier: Programming Language :: Python :: 3.10
Classifier: Programming Language :: Python :: 3.11
Classifier: Programming Language :: Python :: 3 :: Only
Requires-Python: >=3.8, <4
License-File: LICENSE
Requires-Dist: deta >=1.2.0
Requires-Dist: uvicorn >=0.23.2
Requires-Dist: fastapi >=0.103.2
Requires-Dist: attrs >=23.1.0
Requires-Dist: rich >=13.6.0
Requires-Dist: pyjwt >=2.8.0
